GooglePlayStoreScrape.py
GooglePlayStoreScrape-0.0.4.dist-info/LICENSE
GooglePlayStoreScrape-0.0.4.dist-info/METADATA
GooglePlayStoreScrape-0.0.4.dist-info/WHEEL
GooglePlayStoreScrape-0.0.4.dist-info/top_level.txt
GooglePlayStoreScrape-0.0.4.dist-info/RECORD
