Metadata-Version: 2.1
Name: GooglePlayStoreScrape
Version: 0.0.4
Summary: GooglePlayStoreScrape Package for Scraping Play Store Reviews and App Information
Home-page: https://github.com/apurvasijaria/GooglePlayStoreScrape
Author: Apurva Sijaria
License: UNKNOWN
Platform: UNKNOWN
Classifier: Programming Language :: Python :: 3
Classifier: License :: OSI Approved :: MIT License
Classifier: Operating System :: OS Independent
Requires-Python: >=3.7
License-File: LICENSE
Requires-Dist: chromedriver-binary (==91.0.4472.101.0)
Requires-Dist: pandas
Requires-Dist: selenium
Requires-Dist: bs4
